napari_segment_anything/__init__.py
napari_segment_anything/_widget.py
napari_segment_anything/napari.yaml
napari_segment_anything/utils.py
napari_segment_anything/_tests/__init__.py
napari_segment_anything/_tests/test_widget.py
napari_segment_anything-0.1.4.dist-info/LICENSE
napari_segment_anything-0.1.4.dist-info/METADATA
napari_segment_anything-0.1.4.dist-info/WHEEL
napari_segment_anything-0.1.4.dist-info/entry_points.txt
napari_segment_anything-0.1.4.dist-info/top_level.txt
napari_segment_anything-0.1.4.dist-info/RECORD
