Metadata-Version: 2.1
Name: napari-segment-anything
Version: 0.1.4
Summary: Napari plugin of Segment Anything Model (SAM)
Home-page: https://github.com/jookuma/napari-segment-anything
Author: Jordao Bragantini
Author-email: jordao.bragantini@czbiohub.org
License: Apache-2.0
Project-URL: Bug Tracker, https://github.com/jookuma/napari-segment-anything/issues
Project-URL: Documentation, https://github.com/jookuma/napari-segment-anything#README.md
Project-URL: Source Code, https://github.com/jookuma/napari-segment-anything
Project-URL: User Support, https://github.com/jookuma/napari-segment-anything/issues
Classifier: Development Status :: 2 - Pre-Alpha
Classifier: Framework :: napari
Classifier: Intended Audience :: Developers
Classifier: License :: OSI Approved :: Apache Software License
Classifier: Operating System :: OS Independent
Classifier: Programming Language :: Python
Classifier: Programming Language :: Python :: 3
Classifier: Programming Language :: Python :: 3 :: Only
Classifier: Programming Language :: Python :: 3.8
Classifier: Programming Language :: Python :: 3.9
Classifier: Programming Language :: Python :: 3.10
Classifier: Topic :: Scientific/Engineering :: Image Processing
Requires-Python: >=3.8
License-File: LICENSE
Requires-Dist: numpy
Requires-Dist: torch
Requires-Dist: torchvision
Requires-Dist: segment-anything
Requires-Dist: qtpy
Requires-Dist: magicgui
Requires-Dist: napari
Provides-Extra: testing
Requires-Dist: tox ; extra == 'testing'
Requires-Dist: pytest ; extra == 'testing'
Requires-Dist: pytest-cov ; extra == 'testing'
Requires-Dist: pytest-qt ; extra == 'testing'
Requires-Dist: pyqt5 ; extra == 'testing'
